Metadata-Version: 2.4
Name: chatterer
Version: 0.2.6
Summary: The highest-level interface for various LLM APIs.
Requires-Python: >=3.12
Requires-Dist: instructor>=1.11.3
Requires-Dist: langchain>=1.0.2
Requires-Dist: langchain-openai>=1.0.1
Requires-Dist: pillow>=12.0.0
Requires-Dist: regex>=2025.10.23
Requires-Dist: rich>=14.2.0
Requires-Dist: colorama>=0.4.6
Requires-Dist: spargear>=0.2.17
Requires-Dist: dotenv>=0.9.9
Requires-Dist: loguru>=0.7.3
Requires-Dist: langchain-core>=1.0.1
Provides-Extra: dev
Requires-Dist: pyright>=1.1.401; extra == "dev"
Provides-Extra: browser
Requires-Dist: playwright>=1.50.0; extra == "browser"
Provides-Extra: pdf
Requires-Dist: pymupdf>=1.25.4; extra == "pdf"
Requires-Dist: pypdf>=5.4.0; extra == "pdf"
Provides-Extra: markdown
Requires-Dist: markitdown[all]>=0.1.1; extra == "markdown"
Requires-Dist: markdownify>=1.1.0; extra == "markdown"
Requires-Dist: commonmark>=0.9.1; extra == "markdown"
Requires-Dist: mistune>=3.1.3; extra == "markdown"
Provides-Extra: audio
Requires-Dist: pydub>=0.25.1; extra == "audio"
Provides-Extra: video
Requires-Dist: youtube-transcript-api>=1.0.3; extra == "video"
Provides-Extra: windows
Requires-Dist: pywin32>=306; sys_platform == "win32" and extra == "windows"
Provides-Extra: openrouter
Requires-Dist: python-open-router>=0.3.2; extra == "openrouter"
Provides-Extra: langchain-basic-providers
Requires-Dist: langchain-google-genai>=3.0.0; extra == "langchain-basic-providers"
Requires-Dist: langchain-anthropic>=1.0.1; extra == "langchain-basic-providers"
Requires-Dist: langchain-ollama>=1.0.0; extra == "langchain-basic-providers"
Provides-Extra: langchain-extra-providers
Requires-Dist: langchain-aws>=1.0.0; extra == "langchain-extra-providers"
Requires-Dist: langchain-google-vertexai>=3.0.1; extra == "langchain-extra-providers"
Requires-Dist: langchain-huggingface>=1.0.0; extra == "langchain-extra-providers"
Provides-Extra: langchain-providers
Requires-Dist: chatterer[langchain-basic-providers]; extra == "langchain-providers"
Requires-Dist: chatterer[langchain-extra-providers]; extra == "langchain-providers"
Provides-Extra: basic
Requires-Dist: chatterer[langchain-basic-providers]; extra == "basic"
Requires-Dist: chatterer[openrouter]; extra == "basic"
Provides-Extra: standard
Requires-Dist: chatterer[basic]; extra == "standard"
Requires-Dist: chatterer[pdf]; extra == "standard"
Requires-Dist: chatterer[markdown]; extra == "standard"
Requires-Dist: chatterer[video]; extra == "standard"
Requires-Dist: chatterer[audio]; extra == "standard"
Requires-Dist: chatterer[windows]; extra == "standard"
Provides-Extra: all
Requires-Dist: chatterer[standard]; extra == "all"
Requires-Dist: chatterer[langchain-extra-providers]; extra == "all"
Requires-Dist: chatterer[dev]; extra == "all"
Requires-Dist: chatterer[browser]; extra == "all"
